botfb/__init__.py
botfb/mylib.py
lktbotfb-1.3.4.dist-info/LICENSE
lktbotfb-1.3.4.dist-info/METADATA
lktbotfb-1.3.4.dist-info/WHEEL
lktbotfb-1.3.4.dist-info/top_level.txt
lktbotfb-1.3.4.dist-info/RECORD
