Metadata-Version: 2.1
Name: lktbotfb
Version: 1.3.4
Summary: This makes it easy for you to create a chatbot for your Facebook page
Home-page: https://github.com/AmirLouktaila/lktbotfb
Author: Salah Louktaila
Author-email: amir.Louktila@gmail.com
License: MIT
Keywords: chatbot,fbbot,fbchat
Classifier: Development Status :: 5 - Production/Stable
Classifier: Intended Audience :: Education
Classifier: Operating System :: Microsoft :: Windows :: Windows 10
Classifier: License :: OSI Approved :: MIT License
Classifier: Programming Language :: Python :: 3
License-File: LICENSE
Requires-Dist: django
